sla_checker/__init__.py
sla_checker/sla_checker.py
sla_checker-0.0.2.dist-info/LICENSE
sla_checker-0.0.2.dist-info/METADATA
sla_checker-0.0.2.dist-info/WHEEL
sla_checker-0.0.2.dist-info/top_level.txt
sla_checker-0.0.2.dist-info/RECORD
