Metadata-Version: 2.1
Name: sla-checker
Version: 0.0.2
Summary: A python module that will check if two events are within a defined SLA.
Home-page: https://github.com/dainok/sla_checker
Author: Andrea Dainese
Author-email: andrea.dainese@gmail.com
License: GPL-3.0-or-later
Platform: UNKNOWN
Classifier: Programming Language :: Python :: 3
Classifier: Topic :: Software Development
Classifier: Topic :: Software Development :: Libraries :: Python Modules
Requires-Python: >=3.6
